{"input":{"cteatedAt":"2021-02-18T12:17:19.278Z","url":"http://www.openmobilealliance.org/release/LightweightM2M/V1_2-20190124-C/","host":"www.openmobilealliance.org"},"result":{"data":[{"url":"http://www.openmobilealliance.org/release/LightweightM2M/V1_2-20190124-C/OMA-RD-LightweightM2M-V1_2-20190124-C.pdf","file":"OMA-RD-LightweightM2M-V1_2-20190124-C.pdf","status":"Candidate","version":"V1.2","date":"2019-01-24","contentMediaType":"application/pdf","description":"This document represents Lightweight M2M version 1.2 consolidated requirements."}]}}