{"input":{"cteatedAt":"2021-02-17T20:43:52.191Z","url":"http://www.openmobilealliance.org/release/SCOMO/","host":"www.openmobilealliance.org"},"result":{"data":[{"url":"http://www.openmobilealliance.org/release/SCOMO/README.txt","file":"README.txt","status":"","version":"","date":"","contentMediaType":"text/plain"}],"toFollow":[{"url":"http://www.openmobilealliance.org/release/SCOMO/V1_0-20070731-C/","pubVersion":"V1_0-20070731-C"},{"url":"http://www.openmobilealliance.org/release/SCOMO/V1_0-20070918-C/","pubVersion":"V1_0-20070918-C"},{"url":"http://www.openmobilealliance.org/release/SCOMO/V1_0-20081024-C/","pubVersion":"V1_0-20081024-C"},{"url":"http://www.openmobilealliance.org/release/SCOMO/V1_0-20090317-C/","pubVersion":"V1_0-20090317-C"},{"url":"http://www.openmobilealliance.org/release/SCOMO/V1_0-20090519-C/","pubVersion":"V1_0-20090519-C"},{"url":"http://www.openmobilealliance.org/release/SCOMO/V1_0-20090710-C/","pubVersion":"V1_0-20090710-C"},{"url":"http://www.openmobilealliance.org/release/SCOMO/V1_0-20090903-C/","pubVersion":"V1_0-20090903-C"},{"url":"http://www.openmobilealliance.org/release/SCOMO/V1_0-20100401-C/","pubVersion":"V1_0-20100401-C"},{"url":"http://www.openmobilealliance.org/release/SCOMO/V1_0-20111206-A/","pubVersion":"V1_0-20111206-A"},{"url":"http://www.openmobilealliance.org/release/SCOMO/V1_1-20111122-C/","pubVersion":"V1_1-20111122-C"},{"url":"http://www.openmobilealliance.org/release/SCOMO/V1_1-20130521-A/","pubVersion":"V1_1-20130521-A"}]}}